asaaspy-0.32.0.dist-info/METADATA
asaaspy-0.32.0.dist-info/WHEEL
asaaspy-0.32.0.dist-info/entry_points.txt
asaaspy-0.32.0.dist-info/licenses/LICENSE
asaaspy/__init__.py
asaaspy/client/__init__.py
asaaspy/client/base.py
asaaspy/client/resources/__init__.py
asaaspy/client/resources/bank.py
asaaspy/client/resources/customer.py
asaaspy/client/resources/my_account.py
asaaspy/client/resources/payment.py
asaaspy/client/resources/pix.py
asaaspy/client/resources/subaccounts.py
asaaspy/client/resources/transfer.py
asaaspy/constants.py
asaaspy/exceptions.py
asaaspy/log.py
asaaspy/schemas/__init__.py
asaaspy/schemas/base.py
asaaspy/schemas/base_fields.py
asaaspy/schemas/v3/__init__.py
asaaspy/schemas/v3/bank.py
asaaspy/schemas/v3/customer.py
asaaspy/schemas/v3/my_account.py
asaaspy/schemas/v3/payment.py
asaaspy/schemas/v3/pix.py
asaaspy/schemas/v3/subaccount.py
asaaspy/schemas/v3/transfer.py
asaaspy/service.py
asaaspy-0.32.0.dist-info/RECORD
